Metadata-Version: 1.0
Name: crr-distribution-package
Version: 0.1
Summary: Gaussian and Binomial distributions
Home-page: UNKNOWN
Author: Chetan Raj Rupakheti
Author-email: chetanrrk@gmail.com
License: UNKNOWN
Platform: UNKNOWN
